setup.cfg
setup.py
NeedForCryptography.egg-info/PKG-INFO
NeedForCryptography.egg-info/SOURCES.txt
NeedForCryptography.egg-info/dependency_links.txt
NeedForCryptography.egg-info/top_level.txt
crypto/__init__.py
crypto/run_tests.py
crypto/asymmetric/__init__.py
crypto/asymmetric/diffie_hellman_exchange.py
crypto/asymmetric/rsa.py
crypto/symmetric/__init__.py
crypto/symmetric/caeser.py
crypto/symmetric/des.py
crypto/symmetric/des3.py
crypto/symmetric/feistel.py
crypto/symmetric/hill.py
crypto/symmetric/playfair.py
crypto/symmetric/rc6.py
crypto/tests/__init__.py
crypto/tests/caeser.py
crypto/tests/des_des3.py
crypto/tests/diffie_hellman_exchange.py
crypto/tests/el_gamal_signature.py
crypto/tests/feistel.py
crypto/tests/hill.py
crypto/tests/playfair.py
crypto/tests/rsa.py
crypto/tests/shamir_sharing_scheme.py
crypto/tools/__init__.py
crypto/tools/discretelog.py
crypto/tools/doubledict.py
crypto/tools/el_gamal_signature.py
crypto/tools/primes.py
crypto/tools/shamir_sharing_scheme.py
crypto/tools/utilities.py